pghops/__init__.py
pghops/conf/default-test.properties
pghops/conf/default.properties
pghops/init/schemas/pghops/create_schema.sql
pghops/init/schemas/pghops/tables/index.sql
pghops/init/schemas/pghops/tables/version.sql
pghops/init/versions/0000.0000.0000.pghops-init.yaml
pghops/main/__init__.py
pghops/main/create_indexes.py
pghops/main/pghops.py
pghops/main/props.py
pghops/main/psql.py
pghops/main/test.py
pghops/main/utils.py
pghops/tests/__init__.py
pghops/tests/functional_tests.py
pghops/tests/unit_tests.py
pghops-3.0.0.dist-info/COPYING
pghops-3.0.0.dist-info/METADATA
pghops-3.0.0.dist-info/WHEEL
pghops-3.0.0.dist-info/entry_points.txt
pghops-3.0.0.dist-info/top_level.txt
pghops-3.0.0.dist-info/RECORD
