Metadata-Version: 2.1
Name: pghops
Version: 3.0.0
Summary: A highly opionated Postgresql migration tool
Home-page: https://github.com/brewski82/pghops
Author: William Bruschi
Author-email: william.bruschi@gmail.com
License: GPLv3
Keywords: PostgreSQL database migrations
Platform: UNKNOWN
Classifier: Programming Language :: Python :: 3
Classifier: Operating System :: OS Independent
Requires-Python: >=3.7
Requires-Dist: PyYAML
